CHANGES.txt
HACKING.txt
MANIFEST.in
README.txt
build-and-test.sh
default.nix
flake.lock
flake.nix
lib.nix
poetry.lock
pyproject.toml
pytest.ini
setup.cfg
setup.py
shell.nix
smoketest.sh
src/backy/__init__.py
src/backy/backup.py
src/backy/conftest.py
src/backy/daemon.py
src/backy/ext_deps.py
src/backy/fallocate.py
src/backy/logging.py
src/backy/main.py
src/backy/quarantine.py
src/backy/revision.py
src/backy/schedule.py
src/backy/scheduler.py
src/backy/timeout.py
src/backy/utils.py
src/backy.egg-info/PKG-INFO
src/backy.egg-info/SOURCES.txt
src/backy.egg-info/dependency_links.txt
src/backy.egg-info/entry_points.txt
src/backy.egg-info/not-zip-safe
src/backy.egg-info/requires.txt
src/backy.egg-info/top_level.txt
src/backy/backends/__init__.py
src/backy/backends/cowfile.py
src/backy/backends/chunked/__init__.py
src/backy/backends/chunked/chunk.py
src/backy/backends/chunked/file.py
src/backy/backends/chunked/store.py
src/backy/backends/chunked/tests/test_backend.py
src/backy/backends/chunked/tests/test_chunk.py
src/backy/backends/chunked/tests/test_file.py
src/backy/examples/backy.conf
src/backy/sources/__init__.py
src/backy/sources/file.py
src/backy/sources/ceph/__init__.py
src/backy/sources/ceph/diff.py
src/backy/sources/ceph/rbd.py
src/backy/sources/ceph/source.py
src/backy/sources/ceph/tests/conftest.py
src/backy/sources/ceph/tests/nodata.rbddiff
src/backy/sources/ceph/tests/test_ceph_source.py
src/backy/sources/ceph/tests/test_diff.py
src/backy/sources/ceph/tests/test_rbd.py
src/backy/sources/flyingcircus/__init__.py
src/backy/sources/flyingcircus/source.py
src/backy/sources/flyingcircus/tests/test_source.py
src/backy/tests/__init__.py
src/backy/tests/conftest.py
src/backy/tests/test_archive.py
src/backy/tests/test_backup.py
src/backy/tests/test_backy.py
src/backy/tests/test_callback.sh
src/backy/tests/test_daemon.py
src/backy/tests/test_fallocate.py
src/backy/tests/test_main.py
src/backy/tests/test_quarantine.py
src/backy/tests/test_revision.py
src/backy/tests/test_schedule.py
src/backy/tests/test_scheduler.py
src/backy/tests/test_source.py
src/backy/tests/test_timeout.py
src/backy/tests/test_utils.py
src/backy/tests/samples/sample1.rev
src/backy/tests/samples/sample2.rev
