Metadata-Version: 2.1
Name: backy
Version: 2.5.1
Summary: Block-based backup and restore utility for virtual machine images
Home-page: https://bitbucket.org/flyingcircus/backy
Author: Christian Theune <ct@flyingcircus.io>, Christian Kauhaus <kc@flyingcircus.io>, Daniel Kraft <daniel.kraft@d9t.de>
Author-email: mail@flyingcircus.io
License: GPL-3
Keywords: backup
Classifier: Development Status :: 5 - Production/Stable
Classifier: Environment :: Console
Classifier: Intended Audience :: System Administrators
Classifier: License :: OSI Approved :: GNU General Public License v3 (GPLv3)
Classifier: Operating System :: POSIX
Classifier: Programming Language :: Python
Classifier: Programming Language :: Python :: 3
Classifier: Programming Language :: Python :: 3.6
Classifier: Programming Language :: Python :: 3.7
Classifier: Programming Language :: Python :: 3.8
Classifier: Programming Language :: Python :: 3.9
Classifier: Topic :: System :: Archiving :: Backup
Provides-Extra: test
